odoo10_addon_stock_valuation_account_manual_adjustment-10.0.1.1.0-py3.8-nspkg.pth
odoo/addons/stock_valuation_account_manual_adjustment/README.rst
odoo/addons/stock_valuation_account_manual_adjustment/__init__.py
odoo/addons/stock_valuation_account_manual_adjustment/__manifest__.py
odoo/addons/stock_valuation_account_manual_adjustment/init_hook.py
odoo/addons/stock_valuation_account_manual_adjustment/data/stock_valuation_account_manual_adjustment_data.xml
odoo/addons/stock_valuation_account_manual_adjustment/i18n/am.po
odoo/addons/stock_valuation_account_manual_adjustment/i18n/ar.po
odoo/addons/stock_valuation_account_manual_adjustment/i18n/bg.po
odoo/addons/stock_valuation_account_manual_adjustment/i18n/bs.po
odoo/addons/stock_valuation_account_manual_adjustment/i18n/ca.po
odoo/addons/stock_valuation_account_manual_adjustment/i18n/ca_ES.po
odoo/addons/stock_valuation_account_manual_adjustment/i18n/cs.po
odoo/addons/stock_valuation_account_manual_adjustment/i18n/da.po
odoo/addons/stock_valuation_account_manual_adjustment/i18n/de.po
odoo/addons/stock_valuation_account_manual_adjustment/i18n/el_GR.po
odoo/addons/stock_valuation_account_manual_adjustment/i18n/en_AU.po
odoo/addons/stock_valuation_account_manual_adjustment/i18n/en_GB.po
odoo/addons/stock_valuation_account_manual_adjustment/i18n/es.po
odoo/addons/stock_valuation_account_manual_adjustment/i18n/es_AR.po
odoo/addons/stock_valuation_account_manual_adjustment/i18n/es_CL.po
odoo/addons/stock_valuation_account_manual_adjustment/i18n/es_CO.po
odoo/addons/stock_valuation_account_manual_adjustment/i18n/es_CR.po
odoo/addons/stock_valuation_account_manual_adjustment/i18n/es_DO.po
odoo/addons/stock_valuation_account_manual_adjustment/i18n/es_EC.po
odoo/addons/stock_valuation_account_manual_adjustment/i18n/es_ES.po
odoo/addons/stock_valuation_account_manual_adjustment/i18n/es_MX.po
odoo/addons/stock_valuation_account_manual_adjustment/i18n/es_PE.po
odoo/addons/stock_valuation_account_manual_adjustment/i18n/es_PY.po
odoo10_addon_stock_valuation_account_manual_adjustment-10.0.1.1.0.dist-info/METADATA
odoo10_addon_stock_valuation_account_manual_adjustment-10.0.1.1.0.dist-info/WHEEL
odoo10_addon_stock_valuation_account_manual_adjustment-10.0.1.1.0.dist-info/namespace_packages.txt
odoo10_addon_stock_valuation_account_manual_adjustment-10.0.1.1.0.dist-info/top_level.txt
odoo10_addon_stock_valuation_account_manual_adjustment-10.0.1.1.0.dist-info/RECORD
